chemai/__init__.py
chemai/_version.py
chemai/datawrangler.py
chemai/data/README.md
chemai/data/look_and_say.dat
chemai/tests/__init__.py
chemai/tests/test_chemai.py
chemai-0.0.1.dist-info/LICENSE
chemai-0.0.1.dist-info/METADATA
chemai-0.0.1.dist-info/WHEEL
chemai-0.0.1.dist-info/top_level.txt
chemai-0.0.1.dist-info/RECORD
