Metadata-Version: 2.1
Name: chemai
Version: 0.0.1
Summary: UNKNOWN
Author: ai-molssi
Author-email: ai@molssi.org
License: BSD-3-Clause
Platform: UNKNOWN
License-File: LICENSE
